document_preprocessor/__init__.py
document_preprocessor/cli.py
document_preprocessor/core.py
document_preprocessor-2026.1.8.2.dist-info/METADATA
document_preprocessor-2026.1.8.2.dist-info/WHEEL
document_preprocessor-2026.1.8.2.dist-info/entry_points.txt
document_preprocessor-2026.1.8.2.dist-info/licenses/LICENSE
document_preprocessor-2026.1.8.2.dist-info/RECORD
