Metadata-Version: 2.4
Name: document_preprocessor
Version: 2026.1.8.2
Summary: Lightweight library for primary processing of document photographs for ease of subsequent recognition
Project-URL: Homepage, https://github.com/smirnovkirilll/document_preprocessor
Project-URL: Source, https://github.com/smirnovkirilll/document_preprocessor
Project-URL: Issues, https://github.com/smirnovkirilll/document_preprocessor/issues
Author: Kirill Smirnov
License-Expression: Apache-2.0
License-File: LICENSE
Keywords: document-scanner,image-processing,ocr,opencv,pillow
Classifier: Operating System :: OS Independent
Classifier: Programming Language :: Python :: 3
Classifier: Programming Language :: Python :: 3 :: Only
Classifier: Topic :: Multimedia :: Graphics :: Graphics Conversion
Classifier: Topic :: Text Processing :: Linguistic
Requires-Python: >=3.13
Requires-Dist: numpy>=2.2.6
Requires-Dist: opencv-python>=4.12.0.88
Requires-Dist: pillow>=12.0.0
